arvd_ap/__init__.py
arvd_ap/arvd_ap.py
arvd_ap-0.2.0.dist-info/licenses/LICENCE.txt
arvd_ap-0.2.0.dist-info/METADATA
arvd_ap-0.2.0.dist-info/WHEEL
arvd_ap-0.2.0.dist-info/top_level.txt
arvd_ap-0.2.0.dist-info/RECORD
