Metadata-Version: 2.4
Name: arvd_ap
Version: 0.2.0
Summary: My description will help you to pass time and understand my ability of writing codes
Home-page: https://github.com/AravindSreeU/arvd_ap
Author: ARAVIND SREE U
Author-email: uaravindsree@gmail.com
Classifier: Programming Language :: Python :: 3
Classifier: License :: OSI Approved :: MIT License
Classifier: Operating System :: OS Independent
Requires-Python: >=3.6
License-File: LICENCE.txt
Dynamic: author
Dynamic: author-email
Dynamic: classifier
Dynamic: description
Dynamic: description-content-type
Dynamic: home-page
Dynamic: license-file
Dynamic: requires-python
Dynamic: summary
